{
  "date": "2026-02-11",
  "requests": 6,
  "remaining": 84,
  "queries_executed": [
    "devops engineer",
    "cloud engineer",
    "platform engineer",
    "product manager",
    "ui designer",
    "new grad software engineer"
  ],
  "metrics": {
    "jobs_per_query": {
      "devops engineer": [
        10
      ],
      "cloud engineer": [
        10
      ],
      "platform engineer": [
        10
      ],
      "product manager": [
        10
      ],
      "ui designer": [
        10
      ],
      "new grad software engineer": [
        10
      ]
    },
    "total_jobs": 60
  }
}