{
  "timestamp": "2026-02-13T18:57:21.974Z",
  "workflow": {
    "last_commit": "2026-02-13 18:27:36 +0000",
    "commit_message": "Update jobs - 2026-02-13 18:27 UTC"
  },
  "sources": {
    "jsearch": 0,
    "greenhouse": 276,
    "lever": 22,
    "ashby": 5,
    "workday": 0,
    "myworkdayjobs": 15,
    "other": 269,
    "total": 587
  },
  "processing": {
    "current_jobs": 587,
    "seen_jobs_total": 1252,
    "fresh_this_run": 20,
    "pending_queue": 1152
  },
  "quota": {
    "jsearch": "78/90",
    "jsearch_remaining": 12
  },
  "databases": {
    "current_jobs_size": "5.73 MB",
    "seen_jobs_size": "209.93 KB",
    "pending_queue_size": "14.64 MB"
  },
  "health": {
    "current_jobs_exists": true,
    "seen_jobs_exists": true,
    "jsearch_usage_exists": true,
    "pending_queue_exists": true
  },
  "warnings": [
    "Pending queue large: 1152 jobs (consider increasing batch size)",
    "Pending queue file size: 14.64 MB (performance impact)"
  ],
  "errors": []
}